LICENSE
MANIFEST.in
README.md
setup.py
pipshow/__init__.py
pipshow/pipshow.py
pipshow.egg-info/PKG-INFO
pipshow.egg-info/SOURCES.txt
pipshow.egg-info/dependency_links.txt
pipshow.egg-info/entry_points.txt
pipshow.egg-info/requires.txt
pipshow.egg-info/top_level.txt