Metadata-Version: 2.1
Name: pipshow
Version: 1.0.7
Summary: A script to show details of any python package, irrespective of whether its installed or not
Home-page: https://github.com/prahladyeri/pipshow
Author: Prahlad Yeri
Author-email: prahladyeri@yahoo.com
License: MIT
Keywords: pip,setup,installer
Platform: UNKNOWN
Classifier: Programming Language :: Python :: 3
Classifier: License :: OSI Approved :: MIT License
Classifier: Operating System :: OS Independent
